{
  "sector": "water",
  "runs": 50,
  "mean_delta": 0.23760575921343186,
  "min_delta": 0.07277657279930105,
  "max_delta": 0.27479999999999993,
  "p95_delta": 0.27479999999999993,
  "runs_data": [
    {
      "run": 1,
      "before": 0.7252000000000001,
      "after": 1.0,
      "delta": 0.27479999999999993,
      "duration": 29
    },
    {
      "run": 2,
      "before": 0.7252000000000001,
      "after": 0.9206939894131503,
      "delta": 0.19549398941315022,
      "duration": 21
    },
    {
      "run": 3,
      "before": 0.7252000000000001,
      "after": 1.0,
      "delta": 0.27479999999999993,
      "duration": 5
    },
    {
      "run": 4,
      "before": 0.7252000000000001,
      "after": 1.0,
      "delta": 0.27479999999999993,
      "duration": 15
    },
    {
      "run": 5,
      "before": 0.7252000000000001,
      "after": 0.9678196784346227,
      "delta": 0.24261967843462262,
      "duration": 11
    },
    {
      "run": 6,
      "before": 0.7252000000000001,
      "after": 1.0,
      "delta": 0.27479999999999993,
      "duration": 22
    },
    {
      "run": 7,
      "before": 0.7252000000000001,
      "after": 0.7979765727993011,
      "delta": 0.07277657279930105,
      "duration": 5
    },
    {
      "run": 8,
      "before": 0.7252000000000001,
      "after": 0.8826353071938379,
      "delta": 0.1574353071938378,
      "duration": 15
    },
    {
      "run": 9,
      "before": 0.7252000000000001,
      "after": 1.0,
      "delta": 0.27479999999999993,
      "duration": 28
    },
    {
      "run": 10,
      "before": 0.7252000000000001,
      "after": 0.8614198512991711,
      "delta": 0.13621985129917102,
      "duration": 8
    },
    {
      "run": 11,
      "before": 0.7252000000000001,
      "after": 0.9711853945487283,
      "delta": 0.24598539454872825,
      "duration": 11
    },
    {
      "run": 12,
      "before": 0.7252000000000001,
      "after": 0.9583459108006098,
      "delta": 0.23314591080060976,
      "duration": 5
    },
    {
      "run": 13,
      "before": 0.7252000000000001,
      "after": 0.9899538525615195,
      "delta": 0.2647538525615194,
      "duration": 8
    },
    {
      "run": 14,
      "before": 0.7252000000000001,
      "after": 0.9439938554685801,
      "delta": 0.21879385546858,
      "duration": 17
    },
    {
      "run": 15,
      "before": 0.7252000000000001,
      "after": 0.9806114016570515,
      "delta": 0.25541140165705145,
      "duration": 19
    },
    {
      "run": 16,
      "before": 0.7252000000000001,
      "after": 0.972078088839744,
      "delta": 0.24687808883974394,
      "duration": 21
    },
    {
      "run": 17,
      "before": 0.7252000000000001,
      "after": 0.887409004093608,
      "delta": 0.16220900409360794,
      "duration": 7
    },
    {
      "run": 18,
      "before": 0.7252000000000001,
      "after": 1.0,
      "delta": 0.27479999999999993,
      "duration": 21
    },
    {
      "run": 19,
      "before": 0.7252000000000001,
      "after": 1.0,
      "delta": 0.27479999999999993,
      "duration": 29
    },
    {
      "run": 20,
      "before": 0.7252000000000001,
      "after": 1.0,
      "delta": 0.27479999999999993,
      "duration": 28
    },
    {
      "run": 21,
      "before": 0.7252000000000001,
      "after": 0.8930884036369274,
      "delta": 0.16788840363692736,
      "duration": 13
    },
    {
      "run": 22,
      "before": 0.7252000000000001,
      "after": 1.0,
      "delta": 0.27479999999999993,
      "duration": 20
    },
    {
      "run": 23,
      "before": 0.7252000000000001,
      "after": 0.9341990734212178,
      "delta": 0.2089990734212177,
      "duration": 11
    },
    {
      "run": 24,
      "before": 0.7252000000000001,
      "after": 0.9435417051804875,
      "delta": 0.21834170518048746,
      "duration": 21
    },
    {
      "run": 25,
      "before": 0.7252000000000001,
      "after": 1.0,
      "delta": 0.27479999999999993,
      "duration": 30
    },
    {
      "run": 26,
      "before": 0.7252000000000001,
      "after": 1.0,
      "delta": 0.27479999999999993,
      "duration": 25
    },
    {
      "run": 27,
      "before": 0.7252000000000001,
      "after": 1.0,
      "delta": 0.27479999999999993,
      "duration": 30
    },
    {
      "run": 28,
      "before": 0.7252000000000001,
      "after": 1.0,
      "delta": 0.27479999999999993,
      "duration": 28
    },
    {
      "run": 29,
      "before": 0.7252000000000001,
      "after": 1.0,
      "delta": 0.27479999999999993,
      "duration": 14
    },
    {
      "run": 30,
      "before": 0.7252000000000001,
      "after": 1.0,
      "delta": 0.27479999999999993,
      "duration": 26
    },
    {
      "run": 31,
      "before": 0.7252000000000001,
      "after": 0.9984588018229734,
      "delta": 0.27325880182297335,
      "duration": 30
    },
    {
      "run": 32,
      "before": 0.7252000000000001,
      "after": 0.8843373956044722,
      "delta": 0.15913739560447215,
      "duration": 15
    },
    {
      "run": 33,
      "before": 0.7252000000000001,
      "after": 1.0,
      "delta": 0.27479999999999993,
      "duration": 27
    },
    {
      "run": 34,
      "before": 0.7252000000000001,
      "after": 1.0,
      "delta": 0.27479999999999993,
      "duration": 13
    },
    {
      "run": 35,
      "before": 0.7252000000000001,
      "after": 1.0,
      "delta": 0.27479999999999993,
      "duration": 25
    },
    {
      "run": 36,
      "before": 0.7252000000000001,
      "after": 1.0,
      "delta": 0.27479999999999993,
      "duration": 21
    },
    {
      "run": 37,
      "before": 0.7252000000000001,
      "after": 1.0,
      "delta": 0.27479999999999993,
      "duration": 29
    },
    {
      "run": 38,
      "before": 0.7252000000000001,
      "after": 1.0,
      "delta": 0.27479999999999993,
      "duration": 15
    },
    {
      "run": 39,
      "before": 0.7252000000000001,
      "after": 1.0,
      "delta": 0.27479999999999993,
      "duration": 29
    },
    {
      "run": 40,
      "before": 0.7252000000000001,
      "after": 0.9149611538952881,
      "delta": 0.18976115389528803,
      "duration": 9
    },
    {
      "run": 41,
      "before": 0.7252000000000001,
      "after": 0.8892800436864573,
      "delta": 0.16408004368645723,
      "duration": 16
    },
    {
      "run": 42,
      "before": 0.7252000000000001,
      "after": 1.0,
      "delta": 0.27479999999999993,
      "duration": 22
    },
    {
      "run": 43,
      "before": 0.7252000000000001,
      "after": 0.9742155498917476,
      "delta": 0.24901554989174757,
      "duration": 15
    },
    {
      "run": 44,
      "before": 0.7252000000000001,
      "after": 0.8734982329698479,
      "delta": 0.1482982329698478,
      "duration": 14
    },
    {
      "run": 45,
      "before": 0.7252000000000001,
      "after": 1.0,
      "delta": 0.27479999999999993,
      "duration": 14
    },
    {
      "run": 46,
      "before": 0.7252000000000001,
      "after": 1.0,
      "delta": 0.27479999999999993,
      "duration": 23
    },
    {
      "run": 47,
      "before": 0.7252000000000001,
      "after": 0.8029049884824896,
      "delta": 0.07770498848248952,
      "duration": 5
    },
    {
      "run": 48,
      "before": 0.7252000000000001,
      "after": 1.0,
      "delta": 0.27479999999999993,
      "duration": 29
    },
    {
      "run": 49,
      "before": 0.7252000000000001,
      "after": 0.9636860559385177,
      "delta": 0.23848605593851768,
      "duration": 8
    },
    {
      "run": 50,
      "before": 0.7252000000000001,
      "after": 0.933993649031245,
      "delta": 0.20879364903124498,
      "duration": 15
    }
  ]
}
